Metadata-Version: 1.0
Name: cmsplugin-image-gallery
Version: 0.7.2
Summary: A reusable Django app adding django-filer-based galleries to Django-CMS.
